{
  "siteName": "Mayur's site setting test.",
  "siteTagline": "mayur",
  "logoText": "Brand",
  "logoImage": null,
  "navLinks": [
    {
      "label": "Home ",
      "href": "https://www.ikf.co.in/"
    },
    {
      "label": "About Us",
      "href": "/about"
    },
    {
      "label": "Contact",
      "href": "/contact"
    },
    {
      "label": "Shop",
      "href": "/shop"
    },
    {
      "label": "Collections",
      "href": "/Collections"
    }
  ],
  "navCtaLabel": "enquire now ",
  "navCtaLink": "/contact",
  "footerTagline": "",
  "footerLinks": [
    {
      "label": "Youtube ",
      "href": "/services"
    },
    {
      "label": "About",
      "href": "/about"
    },
    {
      "label": "Contact",
      "href": "/contact"
    }
  ],
  "copyrightText": "",
  "googleFontsUrl": "",
  "socialLinks": []
}